dbt/adapters/databend/__init__.py
dbt/adapters/databend/__version__.py
dbt/adapters/databend/column.py
dbt/adapters/databend/connections.py
dbt/adapters/databend/impl.py
dbt/adapters/databend/relation.py
dbt/include/databend/__init__.py
dbt/include/databend/dbt_project.yml
dbt/include/databend/macros/adapters.sql
dbt/include/databend/macros/catalog.sql
dbt_databend-1.1.0.dist-info/LICENSE
dbt_databend-1.1.0.dist-info/METADATA
dbt_databend-1.1.0.dist-info/WHEEL
dbt_databend-1.1.0.dist-info/top_level.txt
dbt_databend-1.1.0.dist-info/RECORD
