Metadata-Version: 2.1
Name: dbt-databend
Version: 1.1.0
Summary: The Databend plugin for dbt (data build tool)
Home-page: https://github.com/silentsokolov/dbt-databend
Author: Dmitriy Sokolov
Author-email: silentsokolov@gmail.com
License: MIT
Keywords: dbt,databend
Platform: any
Classifier: Development Status :: 5 - Production/Stable
Classifier: License :: OSI Approved :: Apache Software License
Classifier: Operating System :: Microsoft :: Windows
Classifier: Operating System :: MacOS :: MacOS X
Classifier: Operating System :: POSIX :: Linux
Classifier: Programming Language :: Python :: 3.6
Classifier: Programming Language :: Python :: 3.7
Classifier: Programming Language :: Python :: 3.8
Classifier: Programming Language :: Python :: 3.9
Requires-Python: >=3.7
License-File: LICENSE
Requires-Dist: dbt-core (~=1.1)
Requires-Dist: mysql-connector-python (<8.1,>=8.0.0)
